taixiu/__init__.py
taixiu/game.py
taixiu_cli-1.1.9.dist-info/METADATA
taixiu_cli-1.1.9.dist-info/WHEEL
taixiu_cli-1.1.9.dist-info/entry_points.txt
taixiu_cli-1.1.9.dist-info/top_level.txt
taixiu_cli-1.1.9.dist-info/RECORD
