Metadata-Version: 2.4
Name: taixiu-cli
Version: 1.1.9
Summary: Tai Xiu (Sic Bo) Casino CLI Game
Requires-Python: <4.0,>=3.8
Requires-Dist: rich
